linearwavetheory/__init__.py
linearwavetheory/_array_shape_preprocessing.py
linearwavetheory/_dispersion_ufuncs.py
linearwavetheory/_numba_settings.py
linearwavetheory/_parametricspectra.py
linearwavetheory/_utils.py
linearwavetheory/dispersion.py
linearwavetheory/settings.py
linearwavetheory/stokes_theory/__init__.py
linearwavetheory/stokes_theory/_estimate_primary_spectra.py
linearwavetheory/stokes_theory/_higher_order_spectra.py
linearwavetheory/stokes_theory/_lagrangian_displacements.py
linearwavetheory/stokes_theory/_nonlinear_dispersion.py
linearwavetheory/stokes_theory/_second_order_coeficients.py
linearwavetheory/stokes_theory/_third_order_coeficients.py
linearwavetheory/stokes_theory/_third_order_statistics.py
linearwavetheory/stokes_theory/_timeseries.py
linearwavetheory/stokes_theory/regular_waves/__init__.py
linearwavetheory/stokes_theory/regular_waves/eularian_velocity_amplitudes.py
linearwavetheory/stokes_theory/regular_waves/eulerian_elevation_amplitudes.py
linearwavetheory/stokes_theory/regular_waves/lagrangian_displacement_amplitudes.py
linearwavetheory/stokes_theory/regular_waves/main.py
linearwavetheory/stokes_theory/regular_waves/mean_properties.py
linearwavetheory/stokes_theory/regular_waves/nonlinear_dispersion.py
linearwavetheory/stokes_theory/regular_waves/phase.py
linearwavetheory/stokes_theory/regular_waves/settings.py
linearwavetheory/stokes_theory/regular_waves/utils.py
linearwavetheory/stokes_theory/regular_waves/vertical_eigen_functions.py
linearwavetheory-0.0.23.dist-info/licenses/LICENSE
linearwavetheory-0.0.23.dist-info/METADATA
linearwavetheory-0.0.23.dist-info/WHEEL
linearwavetheory-0.0.23.dist-info/top_level.txt
linearwavetheory-0.0.23.dist-info/RECORD
